{
    "Aatrox": "assests\\champion\\Aatrox.png",
    "Ahri": "assests\\champion\\Ahri.png",
    "Akali": "assests\\champion\\Akali.png",
    "Akshan": "assests\\champion\\Akshan.png",
    "Alistar": "assests\\champion\\Alistar.png",
    "Ambessa": "assests\\champion\\Ambessa.png",
    "Amumu": "assests\\champion\\Amumu.png",
    "Anivia": "assests\\champion\\Anivia.png",
    "Annie": "assests\\champion\\Annie.png",
    "Aphelios": "assests\\champion\\Aphelios.png",
    "Ashe": "assests\\champion\\Ashe.png",
    "Aurelion Sol": "assests\\champion\\Aurelion Sol.png",
    "Aurora": "assests\\champion\\Aurora.png",
    "Azir": "assests\\champion\\Azir.png",
    "Bard": "assests\\champion\\Bard.png",
    "Bel'Veth": "assests\\champion\\Bel'Veth.png",
    "Blitzcrank": "assests\\champion\\Blitzcrank.png",
    "Brand": "assests\\champion\\Brand.png",
    "Braum": "assests\\champion\\Braum.png",
    "Briar": "assests\\champion\\Briar.png",
    "Caitlyn": "assests\\champion\\Caitlyn.png",
    "Camille": "assests\\champion\\Camille.png",
    "Cassiopeia": "assests\\champion\\Cassiopeia.png",
    "Cho'Gath": "assests\\champion\\Cho'Gath.png",
    "Corki": "assests\\champion\\Corki.png",
    "Darius": "assests\\champion\\Darius.png",
    "Diana": "assests\\champion\\Diana.png",
    "Draven": "assests\\champion\\Draven.png",
    "Dr. Mundo": "assests\\champion\\Dr. Mundo.png",
    "Ekko": "assests\\champion\\Ekko.png",
    "Elise": "assests\\champion\\Elise.png",
    "Evelynn": "assests\\champion\\Evelynn.png",
    "Ezreal": "assests\\champion\\Ezreal.png",
    "Fiddlesticks": "assests\\champion\\Fiddlesticks.png",
    "Fiora": "assests\\champion\\Fiora.png",
    "Fizz": "assests\\champion\\Fizz.png",
    "Galio": "assests\\champion\\Galio.png",
    "Gangplank": "assests\\champion\\Gangplank.png",
    "Garen": "assests\\champion\\Garen.png",
    "Gnar": "assests\\champion\\Gnar.png",
    "Gragas": "assests\\champion\\Gragas.png",
    "Graves": "assests\\champion\\Graves.png",
    "Gwen": "assests\\champion\\Gwen.png",
    "Hecarim": "assests\\champion\\Hecarim.png",
    "Heimerdinger": "assests\\champion\\Heimerdinger.png",
    "Hwei": "assests\\champion\\Hwei.png",
    "Illaoi": "assests\\champion\\Illaoi.png",
    "Irelia": "assests\\champion\\Irelia.png",
    "Ivern": "assests\\champion\\Ivern.png",
    "Janna": "assests\\champion\\Janna.png",
    "Jarvan IV": "assests\\champion\\Jarvan IV.png",
    "Jax": "assests\\champion\\Jax.png",
    "Jayce": "assests\\champion\\Jayce.png",
    "Jhin": "assests\\champion\\Jhin.png",
    "Jinx": "assests\\champion\\Jinx.png",
    "Kai'Sa": "assests\\champion\\Kai'Sa.png",
    "Kalista": "assests\\champion\\Kalista.png",
    "Karma": "assests\\champion\\Karma.png",
    "Karthus": "assests\\champion\\Karthus.png",
    "Kassadin": "assests\\champion\\Kassadin.png",
    "Katarina": "assests\\champion\\Katarina.png",
    "Kayle": "assests\\champion\\Kayle.png",
    "Kayn": "assests\\champion\\Kayn.png",
    "Kennen": "assests\\champion\\Kennen.png",
    "Kha'Zix": "assests\\champion\\Kha'Zix.png",
    "Kindred": "assests\\champion\\Kindred.png",
    "Kled": "assests\\champion\\Kled.png",
    "Kog'Maw": "assests\\champion\\Kog'Maw.png",
    "K'Sante": "assests\\champion\\K'Sante.png",
    "LeBlanc": "assests\\champion\\LeBlanc.png",
    "Lee Sin": "assests\\champion\\Lee Sin.png",
    "Leona": "assests\\champion\\Leona.png",
    "Lillia": "assests\\champion\\Lillia.png",
    "Lissandra": "assests\\champion\\Lissandra.png",
    "Lucian": "assests\\champion\\Lucian.png",
    "Lulu": "assests\\champion\\Lulu.png",
    "Lux": "assests\\champion\\Lux.png",
    "Malphite": "assests\\champion\\Malphite.png",
    "Malzahar": "assests\\champion\\Malzahar.png",
    "Maokai": "assests\\champion\\Maokai.png",
    "Master Yi": "assests\\champion\\Master Yi.png",
    "Milio": "assests\\champion\\Milio.png",
    "Miss Fortune": "assests\\champion\\Miss Fortune.png",
    "Wukong": "assests\\champion\\Wukong.png",
    "Mordekaiser": "assests\\champion\\Mordekaiser.png",
    "Morgana": "assests\\champion\\Morgana.png",
    "Naafiri": "assests\\champion\\Naafiri.png",
    "Nami": "assests\\champion\\Nami.png",
    "Nasus": "assests\\champion\\Nasus.png",
    "Nautilus": "assests\\champion\\Nautilus.png",
    "Neeko": "assests\\champion\\Neeko.png",
    "Nidalee": "assests\\champion\\Nidalee.png",
    "Nilah": "assests\\champion\\Nilah.png",
    "Nocturne": "assests\\champion\\Nocturne.png",
    "Nunu & Willump": "assests\\champion\\Nunu & Willump.png",
    "Olaf": "assests\\champion\\Olaf.png",
    "Orianna": "assests\\champion\\Orianna.png",
    "Ornn": "assests\\champion\\Ornn.png",
    "Pantheon": "assests\\champion\\Pantheon.png",
    "Poppy": "assests\\champion\\Poppy.png",
    "Pyke": "assests\\champion\\Pyke.png",
    "Qiyana": "assests\\champion\\Qiyana.png",
    "Quinn": "assests\\champion\\Quinn.png",
    "Rakan": "assests\\champion\\Rakan.png",
    "Rammus": "assests\\champion\\Rammus.png",
    "Rek'Sai": "assests\\champion\\Rek'Sai.png",
    "Rell": "assests\\champion\\Rell.png",
    "Renata Glasc": "assests\\champion\\Renata Glasc.png",
    "Renekton": "assests\\champion\\Renekton.png",
    "Rengar": "assests\\champion\\Rengar.png",
    "Riven": "assests\\champion\\Riven.png",
    "Rumble": "assests\\champion\\Rumble.png",
    "Ryze": "assests\\champion\\Ryze.png",
    "Samira": "assests\\champion\\Samira.png",
    "Sejuani": "assests\\champion\\Sejuani.png",
    "Senna": "assests\\champion\\Senna.png",
    "Seraphine": "assests\\champion\\Seraphine.png",
    "Sett": "assests\\champion\\Sett.png",
    "Shaco": "assests\\champion\\Shaco.png",
    "Shen": "assests\\champion\\Shen.png",
    "Shyvana": "assests\\champion\\Shyvana.png",
    "Singed": "assests\\champion\\Singed.png",
    "Sion": "assests\\champion\\Sion.png",
    "Sivir": "assests\\champion\\Sivir.png",
    "Skarner": "assests\\champion\\Skarner.png",
    "Smolder": "assests\\champion\\Smolder.png",
    "Sona": "assests\\champion\\Sona.png",
    "Soraka": "assests\\champion\\Soraka.png",
    "Swain": "assests\\champion\\Swain.png",
    "Sylas": "assests\\champion\\Sylas.png",
    "Syndra": "assests\\champion\\Syndra.png",
    "Tahm Kench": "assests\\champion\\Tahm Kench.png",
    "Taliyah": "assests\\champion\\Taliyah.png",
    "Talon": "assests\\champion\\Talon.png",
    "Taric": "assests\\champion\\Taric.png",
    "Teemo": "assests\\champion\\Teemo.png",
    "Thresh": "assests\\champion\\Thresh.png",
    "Tristana": "assests\\champion\\Tristana.png",
    "Trundle": "assests\\champion\\Trundle.png",
    "Tryndamere": "assests\\champion\\Tryndamere.png",
    "Twisted Fate": "assests\\champion\\Twisted Fate.png",
    "Twitch": "assests\\champion\\Twitch.png",
    "Udyr": "assests\\champion\\Udyr.png",
    "Urgot": "assests\\champion\\Urgot.png",
    "Varus": "assests\\champion\\Varus.png",
    "Vayne": "assests\\champion\\Vayne.png",
    "Veigar": "assests\\champion\\Veigar.png",
    "Vel'Koz": "assests\\champion\\Vel'Koz.png",
    "Vex": "assests\\champion\\Vex.png",
    "Vi": "assests\\champion\\Vi.png",
    "Viego": "assests\\champion\\Viego.png",
    "Viktor": "assests\\champion\\Viktor.png",
    "Vladimir": "assests\\champion\\Vladimir.png",
    "Volibear": "assests\\champion\\Volibear.png",
    "Warwick": "assests\\champion\\Warwick.png",
    "Xayah": "assests\\champion\\Xayah.png",
    "Xerath": "assests\\champion\\Xerath.png",
    "Xin Zhao": "assests\\champion\\Xin Zhao.png",
    "Yasuo": "assests\\champion\\Yasuo.png",
    "Yone": "assests\\champion\\Yone.png",
    "Yorick": "assests\\champion\\Yorick.png",
    "Yuumi": "assests\\champion\\Yuumi.png",
    "Zac": "assests\\champion\\Zac.png",
    "Zed": "assests\\champion\\Zed.png",
    "Zeri": "assests\\champion\\Zeri.png",
    "Ziggs": "assests\\champion\\Ziggs.png",
    "Zilean": "assests\\champion\\Zilean.png",
    "Zoe": "assests\\champion\\Zoe.png",
    "Zyra": "assests\\champion\\Zyra.png"
}